{"nodes": [{"id": "c_users_user_documents_github_duofy_lib_services_fb_fb_core_dart", "label": "fb_core.dart", "file_type": "code", "source_file": "lib/services/fb/fb_core.dart", "source_location": null}, {"id": "fb_fb_core_fbcore", "label": "FbCore", "file_type": "code", "source_file": "lib/services/fb/fb_core.dart", "source_location": null}, {"id": "fb_fb_core_filetokenstore", "label": "_FileTokenStore", "file_type": "code", "source_file": "lib/services/fb/fb_core.dart", "source_location": null}, {"id": "fd_tokenstore", "label": "fd.TokenStore", "file_type": "code", "source_file": null, "source_location": null}, {"id": "fb_fb_core_usefiredart", "label": "useFiredart", "file_type": "code", "source_file": "lib/services/fb/fb_core.dart", "source_location": null}, {"id": "bool_get", "label": "bool get", "file_type": "code", "source_file": null, "source_location": null}, {"id": "fb_fb_core_initialized", "label": "_initialized", "file_type": "code", "source_file": "lib/services/fb/fb_core.dart", "source_location": null}, {"id": "static_bool", "label": "static bool", "file_type": "code", "source_file": null, "source_location": null}, {"id": "fb_fb_core_file", "label": "_file", "file_type": "code", "source_file": "lib/services/fb/fb_core.dart", "source_location": null}, {"id": "file", "label": "File", "file_type": "code", "source_file": null, "source_location": null}, {"id": "fb_fb_core_initializeapp", "label": "initializeApp", "file_type": "code", "source_file": "lib/services/fb/fb_core.dart", "source_location": null}, {"id": "fb_fb_core_read", "label": "read", "file_type": "code", "source_file": "lib/services/fb/fb_core.dart", "source_location": null}, {"id": "fb_fb_core_write", "label": "write", "file_type": "code", "source_file": "lib/services/fb/fb_core.dart", "source_location": null}, {"id": "fb_fb_core_delete", "label": "delete", "file_type": "code", "source_file": "lib/services/fb/fb_core.dart", "source_location": null}, {"id": "dart_async", "label": "dart:async", "file_type": "code", "source_file": null, "source_location": null}, {"id": "dart_convert", "label": "dart:convert", "file_type": "code", "source_file": null, "source_location": null}, {"id": "dart_io", "label": "dart:io", "file_type": "code", "source_file": null, "source_location": null}, {"id": "package_flutter_foundation_dart", "label": "package:flutter/foundation.dart", "file_type": "code", "source_file": null, "source_location": null}, {"id": "package_firebase_core_firebase_core_dart", "label": "package:firebase_core/firebase_core.dart", "file_type": "code", "source_file": null, "source_location": null}, {"id": "package_firedart_firedart_dart", "label": "package:firedart/firedart.dart", "file_type": "code", "source_file": null, "source_location": null}, {"id": "package_path_provider_path_provider_dart", "label": "package:path_provider/path_provider.dart", "file_type": "code", "source_file": null, "source_location": null}, {"id": "firebase_options_dart", "label": "../../firebase_options.dart", "file_type": "code", "source_file": null, "source_location": null}], "edges": [{"source": "c_users_user_documents_github_duofy_lib_services_fb_fb_core_dart", "target": "fb_fb_core_fbcore", "relation": "defines", "confidence": "EXTRACTED", "confidence_score": 1.0, "source_file": "lib/services/fb/fb_core.dart", "source_location": null, "weight": 1.0}, {"source": "c_users_user_documents_github_duofy_lib_services_fb_fb_core_dart", "target": "fb_fb_core_filetokenstore", "relation": "defines", "confidence": "EXTRACTED", "confidence_score": 1.0, "source_file": "lib/services/fb/fb_core.dart", "source_location": null, "weight": 1.0}, {"source": "fb_fb_core_filetokenstore", "target": "fd_tokenstore", "relation": "inherits", "confidence": "EXTRACTED", "confidence_score": 1.0, "source_file": "lib/services/fb/fb_core.dart", "source_location": null, "weight": 1.0}, {"source": "c_users_user_documents_github_duofy_lib_services_fb_fb_core_dart", "target": "fb_fb_core_usefiredart", "relation": "defines", "confidence": "EXTRACTED", "confidence_score": 1.0, "source_file": "lib/services/fb/fb_core.dart", "source_location": null, "weight": 1.0}, {"source": "c_users_user_documents_github_duofy_lib_services_fb_fb_core_dart", "target": "bool_get", "relation": "references", "confidence": "EXTRACTED", "confidence_score": 1.0, "source_file": "lib/services/fb/fb_core.dart", "source_location": null, "weight": 1.0, "context": "variable_type"}, {"source": "c_users_user_documents_github_duofy_lib_services_fb_fb_core_dart", "target": "fb_fb_core_initialized", "relation": "defines", "confidence": "EXTRACTED", "confidence_score": 1.0, "source_file": "lib/services/fb/fb_core.dart", "source_location": null, "weight": 1.0}, {"source": "c_users_user_documents_github_duofy_lib_services_fb_fb_core_dart", "target": "static_bool", "relation": "references", "confidence": "EXTRACTED", "confidence_score": 1.0, "source_file": "lib/services/fb/fb_core.dart", "source_location": null, "weight": 1.0, "context": "variable_type"}, {"source": "c_users_user_documents_github_duofy_lib_services_fb_fb_core_dart", "target": "fb_fb_core_file", "relation": "defines", "confidence": "EXTRACTED", "confidence_score": 1.0, "source_file": "lib/services/fb/fb_core.dart", "source_location": null, "weight": 1.0}, {"source": "c_users_user_documents_github_duofy_lib_services_fb_fb_core_dart", "target": "file", "relation": "references", "confidence": "EXTRACTED", "confidence_score": 1.0, "source_file": "lib/services/fb/fb_core.dart", "source_location": null, "weight": 1.0, "context": "variable_type"}, {"source": "c_users_user_documents_github_duofy_lib_services_fb_fb_core_dart", "target": "fb_fb_core_initializeapp", "relation": "defines", "confidence": "EXTRACTED", "confidence_score": 1.0, "source_file": "lib/services/fb/fb_core.dart", "source_location": null, "weight": 1.0}, {"source": "c_users_user_documents_github_duofy_lib_services_fb_fb_core_dart", "target": "fb_fb_core_read", "relation": "defines", "confidence": "EXTRACTED", "confidence_score": 1.0, "source_file": "lib/services/fb/fb_core.dart", "source_location": null, "weight": 1.0}, {"source": "c_users_user_documents_github_duofy_lib_services_fb_fb_core_dart", "target": "fb_fb_core_write", "relation": "defines", "confidence": "EXTRACTED", "confidence_score": 1.0, "source_file": "lib/services/fb/fb_core.dart", "source_location": null, "weight": 1.0}, {"source": "c_users_user_documents_github_duofy_lib_services_fb_fb_core_dart", "target": "fb_fb_core_delete", "relation": "defines", "confidence": "EXTRACTED", "confidence_score": 1.0, "source_file": "lib/services/fb/fb_core.dart", "source_location": null, "weight": 1.0}, {"source": "c_users_user_documents_github_duofy_lib_services_fb_fb_core_dart", "target": "dart_async", "relation": "imports", "confidence": "EXTRACTED", "confidence_score": 1.0, "source_file": "lib/services/fb/fb_core.dart", "source_location": null, "weight": 1.0}, {"source": "c_users_user_documents_github_duofy_lib_services_fb_fb_core_dart", "target": "dart_convert", "relation": "imports", "confidence": "EXTRACTED", "confidence_score": 1.0, "source_file": "lib/services/fb/fb_core.dart", "source_location": null, "weight": 1.0}, {"source": "c_users_user_documents_github_duofy_lib_services_fb_fb_core_dart", "target": "dart_io", "relation": "imports", "confidence": "EXTRACTED", "confidence_score": 1.0, "source_file": "lib/services/fb/fb_core.dart", "source_location": null, "weight": 1.0}, {"source": "c_users_user_documents_github_duofy_lib_services_fb_fb_core_dart", "target": "package_flutter_foundation_dart", "relation": "imports", "confidence": "EXTRACTED", "confidence_score": 1.0, "source_file": "lib/services/fb/fb_core.dart", "source_location": null, "weight": 1.0}, {"source": "c_users_user_documents_github_duofy_lib_services_fb_fb_core_dart", "target": "package_firebase_core_firebase_core_dart", "relation": "imports", "confidence": "EXTRACTED", "confidence_score": 1.0, "source_file": "lib/services/fb/fb_core.dart", "source_location": null, "weight": 1.0}, {"source": "c_users_user_documents_github_duofy_lib_services_fb_fb_core_dart", "target": "package_firedart_firedart_dart", "relation": "imports", "confidence": "EXTRACTED", "confidence_score": 1.0, "source_file": "lib/services/fb/fb_core.dart", "source_location": null, "weight": 1.0}, {"source": "c_users_user_documents_github_duofy_lib_services_fb_fb_core_dart", "target": "package_path_provider_path_provider_dart", "relation": "imports", "confidence": "EXTRACTED", "confidence_score": 1.0, "source_file": "lib/services/fb/fb_core.dart", "source_location": null, "weight": 1.0}, {"source": "c_users_user_documents_github_duofy_lib_services_fb_fb_core_dart", "target": "firebase_options_dart", "relation": "imports", "confidence": "EXTRACTED", "confidence_score": 1.0, "source_file": "lib/services/fb/fb_core.dart", "source_location": null, "weight": 1.0}]}