{"nodes": [{"id": "c_users_user_documents_github_duofy_lib_screens_pdf_folder_screen_dart", "label": "pdf_folder_screen.dart", "file_type": "code", "source_file": "lib/screens/pdf_folder_screen.dart", "source_location": null}, {"id": "screens_pdf_folder_screen_pdffilemeta", "label": "PdfFileMeta", "file_type": "code", "source_file": "lib/screens/pdf_folder_screen.dart", "source_location": null}, {"id": "screens_pdf_folder_screen_pdffolderscreen", "label": "PdfFolderScreen", "file_type": "code", "source_file": "lib/screens/pdf_folder_screen.dart", "source_location": null}, {"id": "statefulwidget", "label": "StatefulWidget", "file_type": "code", "source_file": null, "source_location": null}, {"id": "screens_pdf_folder_screen_pdffolderscreenstate", "label": "_PdfFolderScreenState", "file_type": "code", "source_file": "lib/screens/pdf_folder_screen.dart", "source_location": null}, {"id": "state", "label": "State", "file_type": "code", "source_file": null, "source_location": null}, {"id": "pdffolderscreen", "label": "PdfFolderScreen", "file_type": "code", "source_file": null, "source_location": null}, {"id": "screens_pdf_folder_screen_file", "label": "file", "file_type": "code", "source_file": "lib/screens/pdf_folder_screen.dart", "source_location": null}, {"id": "file", "label": "File", "file_type": "code", "source_file": null, "source_location": null}, {"id": "screens_pdf_folder_screen_unitid", "label": "unitId", "file_type": "code", "source_file": "lib/screens/pdf_folder_screen.dart", "source_location": null}, {"id": "screens_pdf_folder_screen_unitname", "label": "unitName", "file_type": "code", "source_file": "lib/screens/pdf_folder_screen.dart", "source_location": null}, {"id": "screens_pdf_folder_screen_sizekb", "label": "sizeKb", "file_type": "code", "source_file": "lib/screens/pdf_folder_screen.dart", "source_location": null}, {"id": "screens_pdf_folder_screen_directory", "label": "directory", "file_type": "code", "source_file": "lib/screens/pdf_folder_screen.dart", "source_location": null}, {"id": "directory", "label": "Directory", "file_type": "code", "source_file": null, "source_location": null}, {"id": "screens_pdf_folder_screen_linkedbook", "label": "linkedBook", "file_type": "code", "source_file": "lib/screens/pdf_folder_screen.dart", "source_location": null}, {"id": "book", "label": "Book?", "file_type": "code", "source_file": null, "source_location": null}, {"id": "screens_pdf_folder_screen_folderid", "label": "folderId", "file_type": "code", "source_file": "lib/screens/pdf_folder_screen.dart", "source_location": null}, {"id": "screens_pdf_folder_screen_files", "label": "_files", "file_type": "code", "source_file": "lib/screens/pdf_folder_screen.dart", "source_location": null}, {"id": "list", "label": "List", "file_type": "code", "source_file": null, "source_location": null}, {"id": "screens_pdf_folder_screen_isloading", "label": "_isLoading", "file_type": "code", "source_file": "lib/screens/pdf_folder_screen.dart", "source_location": null}, {"id": "screens_pdf_folder_screen_createstate", "label": "createState", "file_type": "code", "source_file": "lib/screens/pdf_folder_screen.dart", "source_location": null}, {"id": "screens_pdf_folder_screen_initstate", "label": "initState", "file_type": "code", "source_file": "lib/screens/pdf_folder_screen.dart", "source_location": null}, {"id": "screens_pdf_folder_screen_loadfiles", "label": "_loadFiles", "file_type": "code", "source_file": "lib/screens/pdf_folder_screen.dart", "source_location": null}, {"id": "screens_pdf_folder_screen_openpdf", "label": "_openPdf", "file_type": "code", "source_file": "lib/screens/pdf_folder_screen.dart", "source_location": null}, {"id": "materialpageroute", "label": "MaterialPageRoute", "file_type": "code", "source_file": null, "source_location": null}, {"id": "screens_pdf_folder_screen_sharepdf", "label": "_sharePdf", "file_type": "code", "source_file": "lib/screens/pdf_folder_screen.dart", "source_location": null}, {"id": "screens_pdf_folder_screen_deletefile", "label": "_deleteFile", "file_type": "code", "source_file": "lib/screens/pdf_folder_screen.dart", "source_location": null}, {"id": "screens_pdf_folder_screen_build", "label": "build", "file_type": "code", "source_file": "lib/screens/pdf_folder_screen.dart", "source_location": null}, {"id": "dart_io", "label": "dart:io", "file_type": "code", "source_file": null, "source_location": null}, {"id": "package_flutter_material_dart", "label": "package:flutter/material.dart", "file_type": "code", "source_file": null, "source_location": null}, {"id": "package_share_plus_share_plus_dart", "label": "package:share_plus/share_plus.dart", "file_type": "code", "source_file": null, "source_location": null}, {"id": "package_syncfusion_flutter_pdfviewer_pdfviewer_dart", "label": "package:syncfusion_flutter_pdfviewer/pdfviewer.dart", "file_type": "code", "source_file": null, "source_location": null}, {"id": "package_lucide_icons_lucide_icons_dart", "label": "package:lucide_icons/lucide_icons.dart", "file_type": "code", "source_file": null, "source_location": null}, {"id": "models_app_models_dart", "label": "../models/app_models.dart", "file_type": "code", "source_file": null, "source_location": null}, {"id": "theme_app_theme_dart", "label": "../theme/app_theme.dart", "file_type": "code", "source_file": null, "source_location": null}, {"id": "widgets_responsive_center_dart", "label": "../widgets/responsive_center.dart", "file_type": "code", "source_file": null, "source_location": null}], "edges": [{"source": "c_users_user_documents_github_duofy_lib_screens_pdf_folder_screen_dart", "target": "screens_pdf_folder_screen_pdffilemeta", "relation": "defines", "confidence": "EXTRACTED", "confidence_score": 1.0, "source_file": "lib/screens/pdf_folder_screen.dart", "source_location": null, "weight": 1.0}, {"source": "c_users_user_documents_github_duofy_lib_screens_pdf_folder_screen_dart", "target": "screens_pdf_folder_screen_pdffolderscreen", "relation": "defines", "confidence": "EXTRACTED", "confidence_score": 1.0, "source_file": "lib/screens/pdf_folder_screen.dart", "source_location": null, "weight": 1.0}, {"source": "screens_pdf_folder_screen_pdffolderscreen", "target": "statefulwidget", "relation": "inherits", "confidence": "EXTRACTED", "confidence_score": 1.0, "source_file": "lib/screens/pdf_folder_screen.dart", "source_location": null, "weight": 1.0}, {"source": "c_users_user_documents_github_duofy_lib_screens_pdf_folder_screen_dart", "target": "screens_pdf_folder_screen_pdffolderscreenstate", "relation": "defines", "confidence": "EXTRACTED", "confidence_score": 1.0, "source_file": "lib/screens/pdf_folder_screen.dart", "source_location": null, "weight": 1.0}, {"source": "screens_pdf_folder_screen_pdffolderscreenstate", "target": "state", "relation": "inherits", "confidence": "EXTRACTED", "confidence_score": 1.0, "source_file": "lib/screens/pdf_folder_screen.dart", "source_location": null, "weight": 1.0}, {"source": "screens_pdf_folder_screen_pdffolderscreenstate", "target": "pdffolderscreen", "relation": "references", "confidence": "EXTRACTED", "confidence_score": 1.0, "source_file": "lib/screens/pdf_folder_screen.dart", "source_location": null, "weight": 1.0}, {"source": "c_users_user_documents_github_duofy_lib_screens_pdf_folder_screen_dart", "target": "screens_pdf_folder_screen_file", "relation": "defines", "confidence": "EXTRACTED", "confidence_score": 1.0, "source_file": "lib/screens/pdf_folder_screen.dart", "source_location": null, "weight": 1.0}, {"source": "c_users_user_documents_github_duofy_lib_screens_pdf_folder_screen_dart", "target": "file", "relation": "references", "confidence": "EXTRACTED", "confidence_score": 1.0, "source_file": "lib/screens/pdf_folder_screen.dart", "source_location": null, "weight": 1.0, "context": "variable_type"}, {"source": "c_users_user_documents_github_duofy_lib_screens_pdf_folder_screen_dart", "target": "screens_pdf_folder_screen_unitid", "relation": "defines", "confidence": "EXTRACTED", "confidence_score": 1.0, "source_file": "lib/screens/pdf_folder_screen.dart", "source_location": null, "weight": 1.0}, {"source": "c_users_user_documents_github_duofy_lib_screens_pdf_folder_screen_dart", "target": "screens_pdf_folder_screen_unitname", "relation": "defines", "confidence": "EXTRACTED", "confidence_score": 1.0, "source_file": "lib/screens/pdf_folder_screen.dart", "source_location": null, "weight": 1.0}, {"source": "c_users_user_documents_github_duofy_lib_screens_pdf_folder_screen_dart", "target": "screens_pdf_folder_screen_sizekb", "relation": "defines", "confidence": "EXTRACTED", "confidence_score": 1.0, "source_file": "lib/screens/pdf_folder_screen.dart", "source_location": null, "weight": 1.0}, {"source": "c_users_user_documents_github_duofy_lib_screens_pdf_folder_screen_dart", "target": "screens_pdf_folder_screen_directory", "relation": "defines", "confidence": "EXTRACTED", "confidence_score": 1.0, "source_file": "lib/screens/pdf_folder_screen.dart", "source_location": null, "weight": 1.0}, {"source": "c_users_user_documents_github_duofy_lib_screens_pdf_folder_screen_dart", "target": "directory", "relation": "references", "confidence": "EXTRACTED", "confidence_score": 1.0, "source_file": "lib/screens/pdf_folder_screen.dart", "source_location": null, "weight": 1.0, "context": "variable_type"}, {"source": "c_users_user_documents_github_duofy_lib_screens_pdf_folder_screen_dart", "target": "screens_pdf_folder_screen_linkedbook", "relation": "defines", "confidence": "EXTRACTED", "confidence_score": 1.0, "source_file": "lib/screens/pdf_folder_screen.dart", "source_location": null, "weight": 1.0}, {"source": "c_users_user_documents_github_duofy_lib_screens_pdf_folder_screen_dart", "target": "book", "relation": "references", "confidence": "EXTRACTED", "confidence_score": 1.0, "source_file": "lib/screens/pdf_folder_screen.dart", "source_location": null, "weight": 1.0, "context": "variable_type"}, {"source": "c_users_user_documents_github_duofy_lib_screens_pdf_folder_screen_dart", "target": "screens_pdf_folder_screen_folderid", "relation": "defines", "confidence": "EXTRACTED", "confidence_score": 1.0, "source_file": "lib/screens/pdf_folder_screen.dart", "source_location": null, "weight": 1.0}, {"source": "c_users_user_documents_github_duofy_lib_screens_pdf_folder_screen_dart", "target": "screens_pdf_folder_screen_files", "relation": "defines", "confidence": "EXTRACTED", "confidence_score": 1.0, "source_file": "lib/screens/pdf_folder_screen.dart", "source_location": null, "weight": 1.0}, {"source": "c_users_user_documents_github_duofy_lib_screens_pdf_folder_screen_dart", "target": "list", "relation": "references", "confidence": "EXTRACTED", "confidence_score": 1.0, "source_file": "lib/screens/pdf_folder_screen.dart", "source_location": null, "weight": 1.0, "context": "variable_type"}, {"source": "c_users_user_documents_github_duofy_lib_screens_pdf_folder_screen_dart", "target": "screens_pdf_folder_screen_isloading", "relation": "defines", "confidence": "EXTRACTED", "confidence_score": 1.0, "source_file": "lib/screens/pdf_folder_screen.dart", "source_location": null, "weight": 1.0}, {"source": "c_users_user_documents_github_duofy_lib_screens_pdf_folder_screen_dart", "target": "screens_pdf_folder_screen_createstate", "relation": "defines", "confidence": "EXTRACTED", "confidence_score": 1.0, "source_file": "lib/screens/pdf_folder_screen.dart", "source_location": null, "weight": 1.0}, {"source": "c_users_user_documents_github_duofy_lib_screens_pdf_folder_screen_dart", "target": "screens_pdf_folder_screen_initstate", "relation": "defines", "confidence": "EXTRACTED", "confidence_score": 1.0, "source_file": "lib/screens/pdf_folder_screen.dart", "source_location": null, "weight": 1.0}, {"source": "c_users_user_documents_github_duofy_lib_screens_pdf_folder_screen_dart", "target": "screens_pdf_folder_screen_loadfiles", "relation": "defines", "confidence": "EXTRACTED", "confidence_score": 1.0, "source_file": "lib/screens/pdf_folder_screen.dart", "source_location": null, "weight": 1.0}, {"source": "c_users_user_documents_github_duofy_lib_screens_pdf_folder_screen_dart", "target": "screens_pdf_folder_screen_openpdf", "relation": "defines", "confidence": "EXTRACTED", "confidence_score": 1.0, "source_file": "lib/screens/pdf_folder_screen.dart", "source_location": null, "weight": 1.0}, {"source": "screens_pdf_folder_screen_openpdf", "target": "materialpageroute", "relation": "navigates", "confidence": "EXTRACTED", "confidence_score": 1.0, "source_file": "lib/screens/pdf_folder_screen.dart", "source_location": null, "weight": 1.0, "context": "route_object"}, {"source": "c_users_user_documents_github_duofy_lib_screens_pdf_folder_screen_dart", "target": "screens_pdf_folder_screen_sharepdf", "relation": "defines", "confidence": "EXTRACTED", "confidence_score": 1.0, "source_file": "lib/screens/pdf_folder_screen.dart", "source_location": null, "weight": 1.0}, {"source": "c_users_user_documents_github_duofy_lib_screens_pdf_folder_screen_dart", "target": "screens_pdf_folder_screen_deletefile", "relation": "defines", "confidence": "EXTRACTED", "confidence_score": 1.0, "source_file": "lib/screens/pdf_folder_screen.dart", "source_location": null, "weight": 1.0}, {"source": "c_users_user_documents_github_duofy_lib_screens_pdf_folder_screen_dart", "target": "screens_pdf_folder_screen_build", "relation": "defines", "confidence": "EXTRACTED", "confidence_score": 1.0, "source_file": "lib/screens/pdf_folder_screen.dart", "source_location": null, "weight": 1.0}, {"source": "c_users_user_documents_github_duofy_lib_screens_pdf_folder_screen_dart", "target": "dart_io", "relation": "imports", "confidence": "EXTRACTED", "confidence_score": 1.0, "source_file": "lib/screens/pdf_folder_screen.dart", "source_location": null, "weight": 1.0}, {"source": "c_users_user_documents_github_duofy_lib_screens_pdf_folder_screen_dart", "target": "package_flutter_material_dart", "relation": "imports", "confidence": "EXTRACTED", "confidence_score": 1.0, "source_file": "lib/screens/pdf_folder_screen.dart", "source_location": null, "weight": 1.0}, {"source": "c_users_user_documents_github_duofy_lib_screens_pdf_folder_screen_dart", "target": "package_share_plus_share_plus_dart", "relation": "imports", "confidence": "EXTRACTED", "confidence_score": 1.0, "source_file": "lib/screens/pdf_folder_screen.dart", "source_location": null, "weight": 1.0}, {"source": "c_users_user_documents_github_duofy_lib_screens_pdf_folder_screen_dart", "target": "package_syncfusion_flutter_pdfviewer_pdfviewer_dart", "relation": "imports", "confidence": "EXTRACTED", "confidence_score": 1.0, "source_file": "lib/screens/pdf_folder_screen.dart", "source_location": null, "weight": 1.0}, {"source": "c_users_user_documents_github_duofy_lib_screens_pdf_folder_screen_dart", "target": "package_lucide_icons_lucide_icons_dart", "relation": "imports", "confidence": "EXTRACTED", "confidence_score": 1.0, "source_file": "lib/screens/pdf_folder_screen.dart", "source_location": null, "weight": 1.0}, {"source": "c_users_user_documents_github_duofy_lib_screens_pdf_folder_screen_dart", "target": "models_app_models_dart", "relation": "imports", "confidence": "EXTRACTED", "confidence_score": 1.0, "source_file": "lib/screens/pdf_folder_screen.dart", "source_location": null, "weight": 1.0}, {"source": "c_users_user_documents_github_duofy_lib_screens_pdf_folder_screen_dart", "target": "theme_app_theme_dart", "relation": "imports", "confidence": "EXTRACTED", "confidence_score": 1.0, "source_file": "lib/screens/pdf_folder_screen.dart", "source_location": null, "weight": 1.0}, {"source": "c_users_user_documents_github_duofy_lib_screens_pdf_folder_screen_dart", "target": "widgets_responsive_center_dart", "relation": "imports", "confidence": "EXTRACTED", "confidence_score": 1.0, "source_file": "lib/screens/pdf_folder_screen.dart", "source_location": null, "weight": 1.0}, {"source": "c_users_user_documents_github_duofy_lib_screens_pdf_folder_screen_dart", "target": "file", "relation": "references", "confidence": "EXTRACTED", "confidence_score": 1.0, "source_file": "lib/screens/pdf_folder_screen.dart", "source_location": null, "weight": 1.0, "context": "type_lookup"}]}